pydjamodb/__init__.py
pydjamodb/attributes.py
pydjamodb/connection.py
pydjamodb/models.py
pydjamodb/queryset.py
pydjamodb/test_runner.py
skip_pydjamodb-0.1.1.dist-info/LICENSE
skip_pydjamodb-0.1.1.dist-info/METADATA
skip_pydjamodb-0.1.1.dist-info/WHEEL
skip_pydjamodb-0.1.1.dist-info/top_level.txt
skip_pydjamodb-0.1.1.dist-info/RECORD
