Metadata-Version: 2.1
Name: skip-pydjamodb
Version: 0.1.1
Summary: Django interface to PyDjamoDB.
Home-page: https://github.com/skip-pay/pydjamodb
Author: Lubos Matl
Author-email: matllubos@gmail.com
License: MIT
Keywords: django,DynamoDB,PyDjamoDB
Classifier: Development Status :: 3 - Alpha
Classifier: Environment :: Web Environment
Classifier: Framework :: Django
Classifier: Intended Audience :: Developers
Classifier: Intended Audience :: End Users/Desktop
Classifier: License :: OSI Approved :: MIT License
Classifier: Natural Language :: Czech
Classifier: Operating System :: OS Independent
Classifier: Programming Language :: Python
Classifier: Topic :: Internet :: WWW/HTTP :: Dynamic Content
Classifier: Topic :: Internet :: WWW/HTTP :: Site Management
License-File: LICENSE
Requires-Dist: django >=4.2
